dowhen/__init__.py
dowhen/callback.py
dowhen/handler.py
dowhen/instrumenter.py
dowhen/trigger.py
dowhen/util.py
dowhen-0.1.0.dist-info/licenses/LICENSE
dowhen-0.1.0.dist-info/licenses/NOTICE
dowhen-0.1.0.dist-info/METADATA
dowhen-0.1.0.dist-info/WHEEL
dowhen-0.1.0.dist-info/top_level.txt
dowhen-0.1.0.dist-info/RECORD
