Metadata-Version: 2.4
Name: dowhen
Version: 0.1.0
Summary: An instrumentation tool for Python
Author-email: Tian Gao <gaogaotiantian@hotmail.com>
License:                                  Apache License
Project-URL: Homepage, https://github.com/gaogaotiantian/dowhen
Classifier: Development Status :: 4 - Beta
Classifier: Programming Language :: Python :: 3.12
Classifier: Programming Language :: Python :: 3.13
Classifier: Intended Audience :: Developers
Classifier: License :: OSI Approved :: Apache Software License
Classifier: Operating System :: MacOS
Classifier: Operating System :: POSIX :: Linux
Classifier: Operating System :: Microsoft :: Windows
Classifier: Topic :: Utilities
Requires-Python: >=3.12
License-File: LICENSE
License-File: NOTICE
Dynamic: license-file
